{"2P+JRVVWH1nX+JY9RdAKLA==":"1-96x96.png","4t5MTpRH+1RjQubRWOITBQ==":"3.png","YnRSnEk0KHU+nmLnM5Im/Q==":"4.png","QkE7vgi4E3gen2wE2Gfwfw==":"5.png","110BOTqfQq1g9JMuRoqJTw==":"descarga%20(2)-240x74.jpg","zVqOj9fo6vwLfWHykIYX8g==":"logotipo-negro-240x120.jpeg","OpeDFgz5QEmrk4pbWKGcaw==":"logotipo-negro-240x120.jpg","+LjA0NQ4mGtE9hAH5ann8Q==":"unnamed-1.jpg","ZNn9vPW4KHb3021q+OmfUQ==":"whatsapp-image-2020-09-09-at-20.17.09.jpeg","PHp7AfSWLkDoM62NQxsDHQ==":"whatsapp-image-2020-09-07-at-19.15.26-1.jpeg","ZJM4DEFslhAbWcGBc3GDag==":"unnamed-1.jpeg","PbQfoEBWEQTg8oo2VJuTOA==":"pp-1.jpg","fNPNIP7iNCLh92QTN4RYrQ==":"whatsapp-image-2020-09-10-at-22.28.10.jpeg","8yDoBLugkM1dionpD52RVg==":"daniela-ferrero.jpg.jpg","pa7MJpQ1MgjhfbYPY6fiig==":"4bb2e7b9-26b0-49df-b484-9f8c77aa6324.jpg","XQGns/KBxLJFW1Kss7vXZg==":"mbr.jpg","nwXepoNtaFCiOXM+J48u+w==":"flat1000x1000075f.u1-1000x667.jpg","y0Uzsko31K8eghhx9F1DJw==":"mbr-1387x929.jpg"}